MANIFEST.in
README.md
prepare-standalone-deployment.py
version.py
backend/__init__.py
backend/app_config.py
backend/application.py
backend/caching.py
backend/cli.py
backend/models.py
backend/t2wml_web.py
backend/utils.py
backend/web_exceptions.py
backend/wikidata_models.py
backend/wsgi.py
backend/migrations/README
backend/migrations/alembic.ini
backend/migrations/env.py
backend/migrations/script.py.mako
backend/migrations/versions/30abf9658b69_.py
backend/migrations/versions/d3efd3ce8b2d_.py
backend/migrations/versions/f397bfd28419_.py
t2wml_standalone.egg-info/PKG-INFO
t2wml_standalone.egg-info/SOURCES.txt
t2wml_standalone.egg-info/dependency_links.txt
t2wml_standalone.egg-info/entry_points.txt
t2wml_standalone.egg-info/not-zip-safe
t2wml_standalone.egg-info/requires.txt
t2wml_standalone.egg-info/top_level.txt
t2wml_standalone-2.0a21.dist-info/METADATA
t2wml_standalone-2.0a21.dist-info/WHEEL
t2wml_standalone-2.0a21.dist-info/entry_points.txt
t2wml_standalone-2.0a21.dist-info/top_level.txt
t2wml_standalone-2.0a21.dist-info/RECORD
