Metadata-Version: 2.1
Name: t2wml-standalone
Version: 2.0a21
Summary: A standalone version of T2WML
Home-page: UNKNOWN
Author: USC ISI
Author-email: UNKNOWN
License: BSD License
Platform: OS Independent
Classifier: Development Status :: 4 - Beta
Classifier: Environment :: Web Environment
Classifier: Framework :: Flask
Classifier: License :: OSI Approved :: BSD License
Classifier: Operating System :: OS Independent
Classifier: Programming Language :: Python
Classifier: Topic :: Internet :: WWW/HTTP :: Dynamic Content
Classifier: Topic :: Software Development :: Libraries :: Application Frameworks
Classifier: Programming Language :: Python :: 3.7
Requires-Dist: flask (>=1.1.2)
Requires-Dist: flask-cors (>=3.0.8)
Requires-Dist: flask-sqlalchemy (>=2.4.1)
Requires-Dist: flask-migrate (>=2.5.3)
Requires-Dist: SPARQLWrapper (>=1.8.4)
Requires-Dist: t2wml-api (==0.0.5)
